line/__init__.py
line/bot.py
line/command.py
line/context.py
line/exceptions.py
line/utils.py
line/ext/login/__init__.py
line/ext/login/client.py
line/ext/login/response.py
line/ext/notify/__init__.py
line/ext/notify/client.py
line/models/__init__.py
line/models/actions.py
line/models/emoji.py
line/models/messages.py
line/models/quick_reply.py
line/models/templates.py
line_messaging_api-0.9.0.dist-info/METADATA
line_messaging_api-0.9.0.dist-info/WHEEL
line_messaging_api-0.9.0.dist-info/licenses/LICENSE
line_messaging_api-0.9.0.dist-info/RECORD
