Metadata-Version: 2.3
Name: line-messaging-api
Version: 0.9.0
Summary: 非阻塞式 LINE Messaging API 封裝
Project-URL: Homepage, https://github.com/seriaati/line.py
Project-URL: Repository, https://github.com/seriaati/line.py.git
Project-URL: Issues, https://github.com/seriaati/line.py/issues
Author-email: seriaati <seria.ati@gmail.com>
License: GNU GENERAL PUBLIC LICENSE
License-File: LICENSE
Requires-Python: >=3.11
Requires-Dist: aiofiles>=24.1.0
Requires-Dist: line-bot-sdk>=3.13.0
Requires-Dist: python-dotenv>=1.0.1
